cpo_tools/__init__.py
cpo_tools/config.py
cpo_tools/cpo_generator.py
cpo_tools/cpo_registry.py
cpo_tools/cpo_verification.py
cpo_tools/cpo_verification_enhanced.py
cpo_tools/src/__init__.py
cpo_tools/src/args.py
cpo_tools/src/llm.py
cpo_tools/src/output.py
cpo_tools/src/process.py
cpo_tools/src/shim_impl.py
cpo_tools/src/trait_impl.py
cpo_tools/templates/concrete_cpo.hpp.jinja2
cpo_tools/templates/doxygen.jinja2
cpo_tools/templates/generic_cpo.hpp.jinja2
cpo_tools/templates/trait_adl_shim.hpp.jinja2
cpo_tools/templates/trait_impl.hpp.jinja2
cpo_tools/templates/macros/dispatch.jinja2
cpo_tools/templates/macros/helpers.jinja2
tincup-1.0.4.dist-info/licenses/LICENSE
tincup-1.0.4.dist-info/METADATA
tincup-1.0.4.dist-info/WHEEL
tincup-1.0.4.dist-info/entry_points.txt
tincup-1.0.4.dist-info/top_level.txt
tincup-1.0.4.dist-info/RECORD
